ssat/__init__.py
ssat/bayesian/__init__.py
ssat/bayesian/base_model.py
ssat/bayesian/base_predictive_model.py
ssat/bayesian/predictive_models.py
ssat/bayesian/stan_files/functions.stan
ssat/bayesian/stan_files/nbinom.stan
ssat/bayesian/stan_files/nbinom_weighted.stan
ssat/bayesian/stan_files/poisson.stan
ssat/bayesian/stan_files/poisson_weighted.stan
ssat/bayesian/stan_files/skellam.stan
ssat/bayesian/stan_files/skellam_weighted.stan
ssat/bayesian/stan_files/skellam_zero.stan
ssat/bayesian/stan_files/skellam_zero_weighted.stan
ssat/benchmark/__init__.py
ssat/data/__init__.py
ssat/data/sample_handball_match_data.parquet
ssat/data/sample_handball_odds_data.parquet
ssat/frequentist/__init__.py
ssat/frequentist/base_model.py
ssat/frequentist/bradley_terry_model.py
ssat/frequentist/gssd_model.py
ssat/frequentist/poisson.py
ssat/frequentist/prp_model.py
ssat/frequentist/toor_model.py
ssat/frequentist/zsd_model.py
ssat/notebooks/__init__.py
ssat/notebooks/bayesian_example.ipynb
ssat/notebooks/bayesian_example.py
ssat/notebooks/frequentist_example.ipynb
ssat/notebooks/frequentist_example.py
ssat/odds/__init__.py
ssat/odds/implied.py
ssat/stats/__init__.py
ssat/stats/skellam.py
ssat/stats/skellam_optim.py
ssat/stats/skellam_rng.py
ssat-0.0.4.dist-info/METADATA
ssat-0.0.4.dist-info/WHEEL
ssat-0.0.4.dist-info/RECORD
