Metadata-Version: 2.4
Name: ssat
Version: 0.0.4
Summary: SSAT: Statistical Sports Analysis Toolkit
Project-URL: Repository, https://github.com/bjrnsa/ssat
Project-URL: Issues, https://github.com/bjrnsa/ssat/issues
Project-URL: Documentation, https://github.com/bjrnsa/ssat/wiki
Project-URL: Changelog, https://github.com/bjrnsa/ssat/blob/main/CHANGELOG.md
Author-email: Bjørn Aagaard <aagaardbs@gmail.com>
License-Expression: MIT
Keywords: analysis,modeling,prediction,sports,statistics
Requires-Python: >=3.10
Requires-Dist: arviz>=0.20.0
Requires-Dist: cmdstanpy>=1.2.5
Requires-Dist: jupyter>=1.1.1
Requires-Dist: matplotlib>=3.10.1
Requires-Dist: numpy>=2.1.3
Requires-Dist: pandas>=2.2.3
Requires-Dist: pyarrow>=20.0.0
Requires-Dist: scipy>=1.15.1
Requires-Dist: seaborn>=0.13.2
